jose/__init__.py
jose/constants.py
jose/exceptions.py
jose/jwk.py
jose/jws.py
jose/jwt.py
jose/utils.py
jose/backends/__init__.py
jose/backends/_asn1.py
jose/backends/base.py
jose/backends/cryptography_backend.py
jose/backends/ecdsa_backend.py
jose/backends/pycrypto_backend.py
jose/backends/rsa_backend.py
python_jose-3.1.0.dist-info/LICENSE
python_jose-3.1.0.dist-info/METADATA
python_jose-3.1.0.dist-info/WHEEL
python_jose-3.1.0.dist-info/top_level.txt
python_jose-3.1.0.dist-info/RECORD
