Metadata-Version: 1.1
Name: python-jose
Version: 3.1.0
Summary: JOSE implementation in Python
Home-page: http://github.com/mpdavis/python-jose
Author: Michael Davis
Author-email: mike.philip.davis@gmail.com
License: MIT
Keywords: jose jws jwe jwt json web token security signing
Platform: UNKNOWN
Classifier: Development Status :: 5 - Production/Stable
Classifier: Intended Audience :: Developers
Classifier: Natural Language :: English
Classifier: License :: OSI Approved :: MIT License
Classifier: Programming Language :: Python
Classifier: Programming Language :: Python :: 2
Classifier: Programming Language :: Python :: 2.7
Classifier: Programming Language :: Python :: 3
Classifier: Programming Language :: Python :: 3.5
Classifier: Programming Language :: Python :: 3.6
Classifier: Programming Language :: Python :: Implementation :: PyPy
Classifier: Topic :: Utilities
